[{"OrderID":"15","Order":"SELL","Symbol":"ASD","Quantity":"3","Price":"3","Route":"ARCA","OrderType":"MKT","Tif":"DAY","OrderDate":"4/1/2022 7:39:13 AM"},{"OrderID":"16","Order":"SELL","Symbol":"ADD","Quantity":"3","Price":"3","Route":"NASDAQ","OrderType":"MKT","Tif":"DAY","OrderDate":"4/1/2022 8:03:47 AM"},{"OrderID":"17","Order":"BUY","Symbol":"ASD","Quantity":"3","Price":"3","Route":"ATS","OrderType":"MKT","Tif":"DAY","OrderDate":"4/1/2022 8:04:15 AM"},{"OrderID":"18","Order":"BUY","Symbol":"ASD","Quantity":"3","Price":"3","Route":"ATS","OrderType":"MKT","Tif":"DAY","OrderDate":"4/1/2022 8:04:18 AM"},{"OrderID":"19","Order":"SHORT","Symbol":"ASD","Quantity":"3","Price":"3","Route":"ATS","OrderType":"MKT","Tif":"DAY","OrderDate":"4/1/2022 8:04:22 AM"},{"OrderID":"20","Order":"SHORT","Symbol":"ASD","Quantity":"3","Price":"3","Route":"NYSE","OrderType":"MKT","Tif":"DAY","OrderDate":"4/1/2022 8:09:47 AM"}]